saylani_db_46165/__init__.py
saylani_db_46165/saylani.py
saylani_db_46165-0.1.dist-info/METADATA
saylani_db_46165-0.1.dist-info/WHEEL
saylani_db_46165-0.1.dist-info/top_level.txt
saylani_db_46165-0.1.dist-info/RECORD
