Metadata-Version: 2.1
Name: saylani-db-46165
Version: 0.1
Summary: This is the Saylani DB Package
Author: Shahzad Ahmed Khan
License: UNKNOWN
Platform: UNKNOWN
